fast2q/__init__.py
fast2q/__main__.py
fast2q/fast2q.py
fast2q/data/D39V_guides.csv
fast2q/data/example.fastq.gz
fast2q-2.8.1.dist-info/licenses/LICENSE
fast2q-2.8.1.dist-info/METADATA
fast2q-2.8.1.dist-info/WHEEL
fast2q-2.8.1.dist-info/entry_points.txt
fast2q-2.8.1.dist-info/top_level.txt
fast2q-2.8.1.dist-info/RECORD
