Metadata-Version: 2.4
Name: fast2q
Version: 2.8.1
Summary: A Python3 program that counts sequence occurences in fastq files.
Home-page: https://github.com/afombravo/2FAST2Q
Author: Afonso M Bravo
Author-email: <afonsombravo@hotmail.com>
Keywords: CRISPRi,CRISPRi-Seq,essentiality,gene fitness,fastq,screening
Classifier: Development Status :: 6 - Mature
Classifier: Intended Audience :: Science/Research
Classifier: Programming Language :: Python :: 3
Classifier: Operating System :: OS Independent
License-File: LICENSE
Requires-Dist: numpy>=1.19.2
Requires-Dist: matplotlib>=3.3.4
Requires-Dist: numba>=0.53.1
Requires-Dist: psutil
Requires-Dist: argparse
Requires-Dist: datetime
Requires-Dist: tqdm>=4.59.0
Requires-Dist: dataclasses
Requires-Dist: tk-tools>=0.1
Requires-Dist: colorama
Dynamic: author
Dynamic: author-email
Dynamic: classifier
Dynamic: description
Dynamic: description-content-type
Dynamic: home-page
Dynamic: keywords
Dynamic: license-file
Dynamic: requires-dist
Dynamic: summary
